{"decls":[{"kind":"export","names":["std.mcp.trust.tlog.merkle_ct_v1.leaf_hash_ct_v1","std.mcp.trust.tlog.merkle_ct_v1.mth_ct_v1","std.mcp.trust.tlog.merkle_ct_v1.node_hash_ct_v1"]},{"body":["begin",["if",["<=","n",1],["return",0],0],["let","p",1],["for","i",0,"n",["begin",["begin",["if",["<",["*","p",2],"n"],["set","p",["*","p",2]],0],0],0]],"p"],"kind":"defn","name":"std.mcp.trust.tlog.merkle_ct_v1._largest_pow2_lt_v1","params":[{"name":"n","ty":"i32"}],"result":"i32"},{"body":["begin",["if",["<=","count",0],["return",["ext.crypto.sha256",["bytes.view_lit",""]]],0],["if",["=","count",1],["begin",["let","line",["std.text.slices.view_at_v1","leaves_lines_text","x7sl_v","start"]],["return",["std.mcp.trust.tlog.merkle_ct_v1.leaf_hash_ct_v1","line"]]],0],["let","k",["std.mcp.trust.tlog.merkle_ct_v1._largest_pow2_lt_v1","count"]],["if",["<=","k",0],["return",["ext.crypto.sha256",["bytes.view_lit",""]]],0],["let","left",["std.mcp.trust.tlog.merkle_ct_v1._mth_range_v1","leaves_lines_text","x7sl_v","start","k"]],["let","right",["std.mcp.trust.tlog.merkle_ct_v1._mth_range_v1","leaves_lines_text","x7sl_v",["+","start","k"],["-","count","k"]]],["std.mcp.trust.tlog.merkle_ct_v1.node_hash_ct_v1",["bytes.view","left"],["bytes.view","right"]]],"decreases":[{"expr":"count","id":"d0"}],"kind":"defn","name":"std.mcp.trust.tlog.merkle_ct_v1._mth_range_v1","params":[{"name":"leaves_lines_text","ty":"bytes_view"},{"name":"x7sl_v","ty":"bytes_view"},{"name":"start","ty":"i32"},{"name":"count","ty":"i32"}],"requires":[{"expr":[">=","count",0],"id":"r0"}],"result":"bytes"},{"body":["begin",["let","v",["vec_u8.with_capacity",["+",1,["view.len","leaf_bytes"]]]],["set","v",["vec_u8.push","v",0]],["set","v",["vec_u8.extend_bytes","v","leaf_bytes"]],["let","b",["vec_u8.into_bytes","v"]],["ext.crypto.sha256",["bytes.view","b"]]],"kind":"defn","name":"std.mcp.trust.tlog.merkle_ct_v1.leaf_hash_ct_v1","params":[{"name":"leaf_bytes","ty":"bytes_view"}],"result":"bytes"},{"body":["begin",["let","x7sl",["std.text.ascii.split_lines_view","leaves_lines_text"]],["let","x7sl_v",["bytes.view","x7sl"]],["let","n",["std.text.slices.count_v1","x7sl_v"]],["std.mcp.trust.tlog.merkle_ct_v1._mth_range_v1","leaves_lines_text","x7sl_v",0,"n"]],"kind":"defn","name":"std.mcp.trust.tlog.merkle_ct_v1.mth_ct_v1","params":[{"name":"leaves_lines_text","ty":"bytes_view"}],"result":"bytes"},{"body":["begin",["let","v",["vec_u8.with_capacity",["+",1,["+",["view.len","left_hash"],["view.len","right_hash"]]]]],["set","v",["vec_u8.push","v",1]],["set","v",["vec_u8.extend_bytes","v","left_hash"]],["set","v",["vec_u8.extend_bytes","v","right_hash"]],["let","b",["vec_u8.into_bytes","v"]],["ext.crypto.sha256",["bytes.view","b"]]],"kind":"defn","name":"std.mcp.trust.tlog.merkle_ct_v1.node_hash_ct_v1","params":[{"name":"left_hash","ty":"bytes_view"},{"name":"right_hash","ty":"bytes_view"}],"result":"bytes"}],"imports":["ext.crypto","std.text.ascii","std.text.slices"],"kind":"module","module_id":"std.mcp.trust.tlog.merkle_ct_v1","schema_version":"x07.x07ast@0.8.0"}
